{"success":8,"child_list":[{"sline":"0","page":"103","aya":"155","sura":"4","eline":"2","epos":"482","id":"914","spos":"0"},{"sline":"2","page":"103","aya":"156","sura":"4","eline":"3","epos":"329","id":"916","spos":"482"},{"sline":"3","page":"103","aya":"157","sura":"4","eline":"6","epos":"362","id":"918","spos":"329"},{"sline":"6","page":"103","aya":"158","sura":"4","eline":"7","epos":"112","id":"921","spos":"362"},{"sline":"7","page":"103","aya":"159","sura":"4","eline":"8","epos":"586","id":"917","spos":"112"},{"sline":"8","page":"103","aya":"160","sura":"4","eline":"10","epos":"198","id":"920","spos":"586"},{"sline":"10","page":"103","aya":"161","sura":"4","eline":"11","epos":"880","id":"915","spos":"198"},{"sline":"11","page":"103","aya":"162","sura":"4","eline":"14","epos":"996","id":"919","spos":"880"}],"page":103}