{"success":7,"child_list":[{"sline":"0","page":"18","aya":"113","sura":"2","eline":"3","epos":"518","id":"150","spos":"0"},{"sline":"3","page":"18","aya":"114","sura":"2","eline":"6","epos":"663","id":"151","spos":"518"},{"sline":"6","page":"18","aya":"115","sura":"2","eline":"7","epos":"1001","id":"152","spos":"663"},{"sline":"8","page":"18","aya":"116","sura":"2","eline":"9","epos":"536","id":"153","spos":"0"},{"sline":"9","page":"18","aya":"117","sura":"2","eline":"10","epos":"796","id":"154","spos":"536"},{"sline":"10","page":"18","aya":"118","sura":"2","eline":"13","epos":"753","id":"155","spos":"796"},{"sline":"13","page":"18","aya":"119","sura":"2","eline":"14","epos":"1000","id":"156","spos":"753"}],"page":18}