{"success":21,"child_list":[{"sline":"0","page":"376","aya":"207","sura":"26","eline":"0","epos":"603","id":"3388","spos":"0"},{"sline":"0","page":"376","aya":"208","sura":"26","eline":"1","epos":"298","id":"3389","spos":"603"},{"sline":"1","page":"376","aya":"209","sura":"26","eline":"1","epos":"797","id":"3390","spos":"298"},{"sline":"1","page":"376","aya":"210","sura":"26","eline":"2","epos":"292","id":"3391","spos":"797"},{"sline":"2","page":"376","aya":"211","sura":"26","eline":"2","epos":"891","id":"3392","spos":"292"},{"sline":"2","page":"376","aya":"212","sura":"26","eline":"3","epos":"455","id":"3393","spos":"891"},{"sline":"3","page":"376","aya":"213","sura":"26","eline":"4","epos":"327","id":"3394","spos":"455"},{"sline":"4","page":"376","aya":"214","sura":"26","eline":"4","epos":"858","id":"3395","spos":"327"},{"sline":"4","page":"376","aya":"215","sura":"26","eline":"5","epos":"684","id":"3396","spos":"858"},{"sline":"5","page":"376","aya":"216","sura":"26","eline":"6","epos":"397","id":"3397","spos":"684"},{"sline":"6","page":"376","aya":"217","sura":"26","eline":"6","epos":"914","id":"3398","spos":"397"},{"sline":"6","page":"376","aya":"218","sura":"26","eline":"7","epos":"362","id":"3399","spos":"914"},{"sline":"7","page":"376","aya":"219","sura":"26","eline":"7","epos":"787","id":"3400","spos":"362"},{"sline":"7","page":"376","aya":"220","sura":"26","eline":"8","epos":"222","id":"3401","spos":"787"},{"sline":"8","page":"376","aya":"221","sura":"26","eline":"8","epos":"869","id":"3402","spos":"222"},{"sline":"8","page":"376","aya":"222","sura":"26","eline":"9","epos":"326","id":"3403","spos":"869"},{"sline":"9","page":"376","aya":"223","sura":"26","eline":"9","epos":"1003","id":"3404","spos":"326"},{"sline":"10","page":"376","aya":"224","sura":"26","eline":"10","epos":"570","id":"3405","spos":"0"},{"sline":"10","page":"376","aya":"225","sura":"26","eline":"11","epos":"260","id":"3406","spos":"570"},{"sline":"11","page":"376","aya":"226","sura":"26","eline":"11","epos":"851","id":"3407","spos":"260"},{"sline":"11","page":"376","aya":"227","sura":"26","eline":"13","epos":"1000","id":"3408","spos":"851"}],"page":376}