{"success":6,"child_list":[{"sline":"2","page":"542","aya":"1","sura":"58","eline":"3","epos":"731","id":"5352","spos":"0"},{"sline":"3","page":"542","aya":"2","sura":"58","eline":"6","epos":"364","id":"5353","spos":"731"},{"sline":"6","page":"542","aya":"3","sura":"58","eline":"8","epos":"538","id":"5354","spos":"364"},{"sline":"8","page":"542","aya":"4","sura":"58","eline":"11","epos":"472","id":"5355","spos":"538"},{"sline":"11","page":"542","aya":"5","sura":"58","eline":"13","epos":"345","id":"5356","spos":"472"},{"sline":"13","page":"542","aya":"6","sura":"58","eline":"14","epos":"995","id":"5357","spos":"345"}],"page":542}