{"success":8,"child_list":[{"sline":"0","page":"6","aya":"30","sura":"2","eline":"3","epos":"106","id":"68","spos":"0"},{"sline":"3","page":"6","aya":"31","sura":"2","eline":"4","epos":"911","id":"69","spos":"106"},{"sline":"4","page":"6","aya":"32","sura":"2","eline":"6","epos":"105","id":"70","spos":"911"},{"sline":"6","page":"6","aya":"33","sura":"2","eline":"8","epos":"524","id":"71","spos":"105"},{"sline":"8","page":"6","aya":"34","sura":"2","eline":"10","epos":"107","id":"72","spos":"524"},{"sline":"10","page":"6","aya":"35","sura":"2","eline":"11","epos":"1003","id":"73","spos":"107"},{"sline":"12","page":"6","aya":"36","sura":"2","eline":"13","epos":"1000","id":"74","spos":"0"},{"sline":"14","page":"6","aya":"37","sura":"2","eline":"14","epos":"1003","id":"75","spos":"0"}],"page":6}